validation/__init__.py
validation/script.py
validation/validate.py
validation/aider/__init__.py
validation/aider/setup.py
validation/aider/aider/__init__.py
validation/aider/aider/args.py
validation/aider/aider/commands.py
validation/aider/aider/diffs.py
validation/aider/aider/dump.py
validation/aider/aider/gui.py
validation/aider/aider/history.py
validation/aider/aider/io.py
validation/aider/aider/linter.py
validation/aider/aider/litellm.py
validation/aider/aider/main.py
validation/aider/aider/mdstream.py
validation/aider/aider/models.py
validation/aider/aider/prompts.py
validation/aider/aider/repo.py
validation/aider/aider/repomap.py
validation/aider/aider/scrape.py
validation/aider/aider/sendchat.py
validation/aider/aider/utils.py
validation/aider/aider/versioncheck.py
validation/aider/aider/voice.py
validation/aider/aider/coders/__init__.py
validation/aider/aider/coders/base_coder.py
validation/aider/aider/coders/base_prompts.py
validation/aider/aider/coders/editblock_coder.py
validation/aider/aider/coders/editblock_fenced_coder.py
validation/aider/aider/coders/editblock_fenced_prompts.py
validation/aider/aider/coders/editblock_func_coder.py
validation/aider/aider/coders/editblock_func_prompts.py
validation/aider/aider/coders/editblock_prompts.py
validation/aider/aider/coders/search_replace.py
validation/aider/aider/coders/single_wholefile_func_coder.py
validation/aider/aider/coders/single_wholefile_func_prompts.py
validation/aider/aider/coders/udiff_coder.py
validation/aider/aider/coders/udiff_prompts.py
validation/aider/aider/coders/wholefile_coder.py
validation/aider/aider/coders/wholefile_func_coder.py
validation/aider/aider/coders/wholefile_func_prompts.py
validation/aider/aider/coders/wholefile_prompts.py
validation/aider/benchmark/__init__.py
validation/aider/benchmark/benchmark.py
validation/aider/benchmark/over_time.py
validation/aider/benchmark/plots.py
validation/aider/benchmark/prompts.py
validation/aider/benchmark/refactor_tools.py
validation_framework-0.1.2.dist-info/METADATA
validation_framework-0.1.2.dist-info/WHEEL
validation_framework-0.1.2.dist-info/top_level.txt
validation_framework-0.1.2.dist-info/RECORD
