Metadata-Version: 2.1
Name: validation_framework
Version: 0.1.2
Summary: A framework for validating LLM responses on various criteria.
Home-page: https://github.com/yourusername/validation_framework
Author: Your Name
Author-email: your.email@example.com
License: MIT
Classifier: Programming Language :: Python :: 3
Classifier: License :: OSI Approved :: MIT License
Classifier: Operating System :: OS Independent
Requires-Python: >=3.6
